duplicity_backup_s3/__init__.py
duplicity_backup_s3/__main__.py
duplicity_backup_s3/cli.py
duplicity_backup_s3/config.py
duplicity_backup_s3/defaults.py
duplicity_backup_s3/duplicity_s3.py
duplicity_backup_s3/py.typed
duplicity_backup_s3/utils.py
duplicity_backup_s3/commands/__init__.py
duplicity_backup_s3/commands/cleanup.py
duplicity_backup_s3/commands/incr.py
duplicity_backup_s3/commands/init.py
duplicity_backup_s3/commands/list.py
duplicity_backup_s3/commands/remove.py
duplicity_backup_s3/commands/restore.py
duplicity_backup_s3/commands/status.py
duplicity_backup_s3/commands/verify.py
duplicity_backup_s3/files/config.template.yaml
duplicity_backup_s3/files/config_schema.yaml
duplicity_backup_s3-1.2.1.dist-info/LICENSE
duplicity_backup_s3-1.2.1.dist-info/METADATA
duplicity_backup_s3-1.2.1.dist-info/WHEEL
duplicity_backup_s3-1.2.1.dist-info/entry_points.txt
duplicity_backup_s3-1.2.1.dist-info/top_level.txt
duplicity_backup_s3-1.2.1.dist-info/RECORD
