Metadata-Version: 2.1
Name: duplicity-backup-s3
Version: 1.2.1
Summary: Duplicity backup to S3 for production servers using simple yaml config file.
Home-page: https://github.com/jberends/duplicity_backup
Author: Jochem Berends
Author-email: jberends@jbits.nl
License: Apache Software License 2.0
Project-URL: Changelog, https://github.com/jberends/duplicity_backup/blob/master/CHANGELOG.md
Project-URL: Contributors, https://github.com/jberends/duplicity_backup/blob/master/CONTRIBUTORS.md
Project-URL: Source, https://github.com/jberends/duplicity_backup
Project-URL: Tracker, https://github.com/jberends/duplicity_backup/issues
Project-URL: Readme, https://github.com/jberends/duplicity_backup/blob/master/README.md
Keywords: duplicity_backup_s3
Classifier: Development Status :: 5 - Production/Stable
Classifier: Intended Audience :: Developers
Classifier: Intended Audience :: System Administrators
Classifier: License :: OSI Approved :: Apache Software License
Classifier: Environment :: Console
Classifier: Operating System :: POSIX
Classifier: Natural Language :: English
Classifier: Programming Language :: Python :: 3 :: Only
Classifier: Programming Language :: Python :: 3
Classifier: Programming Language :: Python :: 3.6
Classifier: Programming Language :: Python :: 3.7
Classifier: Programming Language :: Python :: 3.8
Classifier: Programming Language :: Python :: 3.9
Classifier: Programming Language :: Python :: 3.10
Classifier: Programming Language :: Python :: 3.11
Classifier: Programming Language :: Python :: Implementation :: PyPy
Classifier: Programming Language :: Python :: Implementation :: CPython
Classifier: Topic :: System :: Archiving :: Backup
Classifier: Topic :: System :: Archiving :: Compression
Classifier: Topic :: System :: Archiving :: Mirroring
Requires-Python: >=3.6
License-File: LICENSE
Requires-Dist: Click (>=7.0)
Requires-Dist: PyYAML
Requires-Dist: envparse
Requires-Dist: appdirs
Requires-Dist: cerberus
